{
  "auto_collapse" : 10.0,
  "bg_color" : [ 0.4705880, 0.4705880, 0.4705880 ],
  "body" : [
    [ 0, 0, 0, 0, 0, 0, 0, 0 ],
    [ 0, 0, 0, 0, 0, 0, 0, 0 ],
    [ 0, 0, 0, -1, -1, 0, 0, 0 ],
    [ 0, 0, 0, -1, -1, 0, 0, 0 ],
    [ 0, 0, 0, 0, 0, 0, 0, 0 ],
    [ 0, 0, 0, 0, 0, 0, 0, 0 ],
    [ 0, 0, 0, 0, 0, 0, 0, 0 ],
    [ 0, 0, 0, 0, 0, 0, 0, 0 ],
    [ 0, 0, 0, 0, 0, 0, 0, 0 ],
    [ 0, 0, 0, 0, 0, 0, 0, 0 ],
    [ -1, -1, 0, 0, 0, 0, -1, -1 ],
    [ -1, -1, 0, 0, 0, 0, -1, -1 ],
    [ 0, 0, 0, 0, 0, 0, 0, 0 ],
    [ 0, 0, 0, 0, 0, 0, 0, 0 ],
    [ 0, 0, 0, -1, -1, 0, 0, 0 ],
    [ 0, 0, 0, -1, -1, 0, 0, 0 ],
    [ 0, 0, 0, -1, -1, 0, 0, 0 ],
    [ 0, 0, 0, -1, -1, 0, 0, 0 ],
    [ 0, 0, 0, 0, 0, 0, 0, 0 ],
    [ 0, 0, 0, 0, 0, 0, 0, 0 ],
    [ 0, 0, 0, 0, 0, 0, 0, 0 ],
    [ 0, 0, 0, 0, 0, 0, 0, 0 ],
    [ -1, -1, 0, 0, 0, 0, -1, -1 ],
    [ -1, -1, 0, 0, 0, 0, -1, -1 ],
    [ 0, 0, 0, 0, 0, 0, 0, 0 ]
  ],
  "build_speed" : 1.100000023841858,
  "collapse_speed" : 1.200000047683716,
  "color" : [ 0, 0.60, 0.2666670 ],
  "falling" : [
    {
      "delay" : 0,
      "entry" : [ 1, 0, 3 ],
      "interval" : 2
    },
    {
      "delay" : 1,
      "entry" : [ 6, 0, 3 ],
      "interval" : 2
    },
    {
      "delay" : 0,
      "entry" : [ 3, 0, 11 ],
      "interval" : 2
    },
    {
      "delay" : 0,
      "entry" : [ 4, 0, 11 ],
      "interval" : 2
    },
    {
      "delay" : 1,
      "entry" : [ 2, 0, 23 ],
      "interval" : 2
    },
    {
      "delay" : 0,
      "entry" : [ 3, 0, 23 ],
      "interval" : 2
    },
    {
      "delay" : 0,
      "entry" : [ 4, 0, 23 ],
      "interval" : 2
    },
    {
      "delay" : 1,
      "entry" : [ 5, 0, 23 ],
      "interval" : 2
    }
  ],
  "items" : [
    [ 1, 0, 5 ],
    [ 6, 0, 5 ],
    [ 1, 0, 18 ],
    [ 6, 0, 18 ]
  ],
  "light_tween" : "default",
  "moving" : [
    {
      "entry" : [ 1, 0, 16 ],
      "pattern" : [ 6, 0, 4, 0, 4, 0, 6, 0 ]
    },
    {
      "entry" : [ 6, 0, 16 ],
      "pattern" : [ 4, 0, 6, 0, 6, 0, 4, 0 ]
    }
  ],
  "pickable" : 1,
  "x_offset" : 0
}
